<?xml version="1.0"?>
<config>
    <modules>
<!-- 2023-12-19 Dmitrii Fediuk https://upwork.com/fl/mage2pro
"Delete the unused `Mage_Install` module": https://github.com/thehcginstitute-com/m1/issues/56 -->
        <Mage_Admin>
            <active>true</active>
            <codePool>core</codePool>
            <depends>
               <Mage_Core/>
            </depends>
        </Mage_Admin>
        <Mage_Rule>
            <active>true</active>
            <codePool>core</codePool>
            <depends>
                <Mage_Core/>
            </depends>
        </Mage_Rule>
        <Mage_Adminhtml>
            <active>true</active>
            <codePool>core</codePool>
            <depends>
                <Mage_Admin/>
            </depends>
        </Mage_Adminhtml>
        <Mage_AdminNotification>
            <active>true</active>
            <codePool>core</codePool>
            <depends>
               <Mage_Core/>
               <Mage_Adminhtml/>
            </depends>
        </Mage_AdminNotification>
        <Mage_Cron>
            <active>true</active>
            <codePool>core</codePool>
            <depends>
                <Mage_Core/>
            </depends>
        </Mage_Cron>
        <Mage_Directory>
            <active>true</active>
            <codePool>core</codePool>
            <depends>
                <Mage_Core/>
            </depends>
        </Mage_Directory>
        <Mage_Customer>
            <active>true</active>
            <codePool>core</codePool>
            <depends>
                <Mage_Eav/>
                <Mage_Dataflow/>
                <Mage_Directory/>
            </depends>
        </Mage_Customer>
        <Mage_Catalog>
            <active>true</active>
            <codePool>core</codePool>
            <depends>
                <Mage_Eav/>
                <Mage_Dataflow/>
                <Mage_Cms/>
                <Mage_Index/>
            </depends>
        </Mage_Catalog>
        <Mage_CatalogRule>
            <active>true</active>
            <codePool>core</codePool>
            <depends>
                <Mage_Rule/>
                <Mage_Catalog/>
                <Mage_Customer/>
            </depends>
        </Mage_CatalogRule>
        <Mage_CatalogIndex>
            <active>true</active>
            <codePool>core</codePool>
            <depends>
                <Mage_Catalog/>
                <Mage_Eav/>
                <Mage_CatalogRule/>
            </depends>
        </Mage_CatalogIndex>
        <Mage_CatalogSearch>
            <active>true</active>
            <codePool>core</codePool>
            <depends>
                <Mage_Catalog/>
            </depends>
        </Mage_CatalogSearch>
        <Mage_Sales>
            <active>true</active>
            <codePool>core</codePool>
            <depends>
                <Mage_Rule/>
                <Mage_Catalog/>
                <Mage_Customer/>
                <Mage_Payment/>
            </depends>
        </Mage_Sales>
        <Mage_SalesRule>
            <active>true</active>
            <codePool>core</codePool>
            <depends>
                <Mage_Rule/>
                <Mage_Catalog/>
                <Mage_Sales/>
            </depends>
        </Mage_SalesRule>
        <Mage_Checkout>
            <active>true</active>
            <codePool>core</codePool>
            <depends>
                <Mage_Sales/>
                <Mage_CatalogInventory/>
            </depends>
        </Mage_Checkout>
        <Mage_Shipping>
            <active>true</active>
            <codePool>core</codePool>
            <depends>
                <Mage_Core/>
                <Mage_Catalog/>
            </depends>
        </Mage_Shipping>
        <Mage_Payment>
            <active>true</active>
            <codePool>core</codePool>
            <depends>
                <Mage_Core/>
                <Mage_Catalog/>
            </depends>
        </Mage_Payment>
<!-- 2024-02-04 Dmitrii Fediuk https://upwork.com/fl/mage2pro
1) "Delete the unused `Mage_Paygate` module": https://github.com/thehcginstitute-com/m1/issues/354
2) "Delete the unused `Mage_Paypal` module": https://github.com/thehcginstitute-com/m1/issues/356
3) "Delete the unused `Mage_PaypalUk` module": https://github.com/thehcginstitute-com/m1/issues/357
4) "Delete the unused `Mage_GoogleCheckout` module": https://github.com/thehcginstitute-com/m1/issues/365
2024-02-05 Dmitrii Fediuk https://upwork.com/fl/mage2pro
"Delete the unused `Mage_Usa` module": https://github.com/thehcginstitute-com/m1/issues/374 -->
        <Mage_Log>
            <active>true</active>
            <codePool>core</codePool>
            <depends>
                <Mage_Core/>
                <Mage_Customer/>
            </depends>
        </Mage_Log>
<!-- 2023-12-19 Dmitrii Fediuk https://upwork.com/fl/mage2pro
"Delete the unused `Mage_Backup` module": https://github.com/thehcginstitute-com/m1/issues/39
2024-02-04 Dmitrii Fediuk https://upwork.com/fl/mage2pro
"Delete the unused `Mage_Poll` module": https://github.com/thehcginstitute-com/m1/issues/367 -->
        <Mage_Rating>
            <active>true</active>
            <codePool>core</codePool>
            <depends>
                <Mage_Core/>
        <Mage_Review/>
            </depends>
        </Mage_Rating>
        <Mage_Review>
            <active>true</active>
            <codePool>core</codePool>
            <depends>
                <Mage_Catalog/>
                <Mage_Core/>
            </depends>
        </Mage_Review>
<!-- 2024-02-05 Dmitrii Fediuk https://upwork.com/fl/mage2pro
"Delete the unused `Mage_Tag` module": https://github.com/thehcginstitute-com/m1/issues/372 -->
        <Mage_Cms>
            <active>true</active>
            <codePool>core</codePool>
            <depends>
                <Mage_Uploader/>
            </depends>
        </Mage_Cms>
        <Mage_Reports>
            <active>true</active>
            <codePool>core</codePool>
            <depends>
                <Mage_Customer/>
                <Mage_Catalog/>
                <Mage_Sales/>
                <Mage_Cms/>
            </depends>
        </Mage_Reports>
        <Mage_Newsletter>
            <active>true</active>
            <codePool>core</codePool>
            <depends>
                <Mage_Core/>
                <Mage_Customer/>
                <Mage_Eav/>
                <Mage_Widget/>
            </depends>
        </Mage_Newsletter>
        <Mage_Tax>
            <active>true</active>
            <codePool>core</codePool>
            <depends>
                <Mage_Catalog/>
                <Mage_Customer/>
            </depends>
        </Mage_Tax>
        <Mage_Wishlist>
            <active>true</active>
            <codePool>core</codePool>
            <depends>
                <Mage_Customer/>
                <Mage_Catalog/>
            </depends>
        </Mage_Wishlist>
<!-- 2024-01-09 Dmitrii Fediuk https://upwork.com/fl/mage2pro
"Delete the `Mage_GoogleAnalytics` module because it is unused (the `Tatvic_Uaee` module is used instead)":
https://github.com/thehcginstitute-com/m1/issues/135 -->
        <Mage_CatalogInventory>
            <active>true</active>
            <codePool>core</codePool>
            <depends>
                <Mage_Catalog/>
            </depends>
        </Mage_CatalogInventory>
        <Mage_GiftMessage>
            <active>true</active>
            <codePool>core</codePool>
            <depends>
                <Mage_Catalog/>
                <Mage_Sales/>
             </depends>
        </Mage_GiftMessage>
        <Mage_Sendfriend>
            <active>true</active>
            <codePool>core</codePool>
             <depends>
                <Mage_Catalog/>
             </depends>
        </Mage_Sendfriend>
        <Mage_Media>
            <active>true</active>
            <codePool>core</codePool>
            <depends>
                <Mage_Core/>
             </depends>
        </Mage_Media>
        <Mage_Sitemap>
            <active>true</active>
            <codePool>core</codePool>
            <depends>
                <Mage_Catalog/>
             </depends>
        </Mage_Sitemap>
        <Mage_Contacts>
            <active>true</active>
            <codePool>core</codePool>
            <depends>
                <Mage_Core/>
            </depends>
        </Mage_Contacts>
        <Mage_Dataflow>
            <active>true</active>
            <codePool>core</codePool>
            <depends>
                <Mage_Core/>
            </depends>
        </Mage_Dataflow>
<!-- 2024-02-04 Dmitrii Fediuk https://upwork.com/fl/mage2pro
"Delete the unused `Mage_Rss` module": https://github.com/thehcginstitute-com/m1/issues/368 -->
        <Mage_ProductAlert>
            <active>true</active>
            <codePool>core</codePool>
            <depends>
                <Mage_Catalog/>
                <Mage_Customer/>
            </depends>
        </Mage_ProductAlert>
        <Mage_Index>
            <active>true</active>
            <codePool>core</codePool>
            <depends>
                <Mage_Core/>
            </depends>
        </Mage_Index>
        <Mage_Uploader>
            <active>true</active>
            <codePool>core</codePool>
            <depends>
                <Mage_Core/>
            </depends>
        </Mage_Uploader>
    </modules>
</config>
