<?xml version="1.0"?>
<!--
/**
 * @author Amasty Team
 * @copyright Copyright (c) 2017 Amasty (https://www.amasty.com)
 * @package Amasty_Base
 */
-->
<config>
    <acl>
        <resources>
            <all>
                <title>Allow Everything</title>
            </all>
            <admin>
                <children>
                    <system>
                        <children>
                            <config>
                                <children>
                                    <ambase translate="title">
                                        <title>Amasty - Extensions Information</title>
                                    </ambase>
<!-- 2024-02-18 Dmitrii Fediuk https://upwork.com/fl/mage2pro
"Prevent Amasty from spamming the Magento's backend": https://github.com/thehcginstitute-com/m1/issues/380 -->
                                </children>
                            </config>
                        </children>
                    </system>
                </children>
            </admin>
        </resources>
    </acl>
<!-- 2024-02-18 Dmitrii Fediuk https://upwork.com/fl/mage2pro
"Prevent Amasty from spamming the Magento's backend": https://github.com/thehcginstitute-com/m1/issues/380 -->
    <translate>
        <modules>
            <Amasty_Base>
                <files>
                    <default>Amasty_Base.csv</default>
                </files>
            </Amasty_Base>
        </modules>
    </translate>
</config>